marcel_fse/__init__.py
marcel_fse/inputs.py
marcel_fse/vectors.py
marcel_fse/models/__init__.py
marcel_fse/models/average.py
marcel_fse/models/base_s2v.py
marcel_fse/models/sentencevectors.py
marcel_fse/models/sif.py
marcel_fse/models/usif.py
marcel_fse/models/utils.py
marcel_fse/models/view.py
marcel_fse-1.7.dist-info/METADATA
marcel_fse-1.7.dist-info/WHEEL
marcel_fse-1.7.dist-info/top_level.txt
marcel_fse-1.7.dist-info/RECORD
