Metadata-Version: 2.1
Name: marcel-fse
Version: 1.7
Summary: Library to get sentence vectors using SIF and uSIF
Author: Marcel Tino
Author-email: <marceltino92@gmail.com>
Requires-Dist: gensim
Requires-Dist: nltk
Requires-Dist: pandas
Requires-Dist: wordfreq
